py2exe_gui/Constants/__init__.py
py2exe_gui/Constants/app_constants.py
py2exe_gui/Constants/packaging_constants.py
py2exe_gui/Constants/python_env_constants.py
py2exe_gui/Constants/runtime_info.py
py2exe_gui/Core/__init__.py
py2exe_gui/Core/packaging.py
py2exe_gui/Core/packaging_task.py
py2exe_gui/Core/subprocess_tool.py
py2exe_gui/Core/validators.py
src/py2exe_gui/Resources/COMPILED_RESOURCES.py
py2exe_gui/Utilities/__init__.py
py2exe_gui/Utilities/open_qfile.py
py2exe_gui/Utilities/platform_specifc_funcs.py
py2exe_gui/Utilities/python_env.py
py2exe_gui/Utilities/qobject_tr.py
py2exe_gui/Widgets/__init__.py
py2exe_gui/Widgets/add_data_widget.py
py2exe_gui/Widgets/arguments_browser.py
py2exe_gui/Widgets/center_widget.py
py2exe_gui/Widgets/dialog_widgets.py
py2exe_gui/Widgets/main_window.py
py2exe_gui/Widgets/multi_item_edit_widget.py
py2exe_gui/Widgets/pyenv_combobox.py
py2exe_gui/Widgets/pyinstaller_option_widget.py
py2exe_gui/Widgets/subprocess_widget.py
py2exe_gui/__init__.py
py2exe_gui/__main__.py
py2exe_gui-0.3.1.dist-info/LICENSE
py2exe_gui-0.3.1.dist-info/METADATA
py2exe_gui-0.3.1.dist-info/WHEEL
py2exe_gui-0.3.1.dist-info/entry_points.txt
py2exe_gui-0.3.1.dist-info/RECORD
