Metadata-Version: 2.1
Name: py2exe-gui
Version: 0.3.1
Summary: GUI for PyInstaller, based on PySide6
Home-page: https://github.com/muziing/Py2exe-GUI
License: GPL-3.0-or-later
Keywords: PyInstaller,GUI,PySide6
Author: muzing
Author-email: muzi2001@foxmail.com
Requires-Python: >=3.8,<3.13
Classifier: Development Status :: 4 - Beta
Classifier: License :: OSI Approved :: GNU General Public License v3 or later (GPLv3+)
Classifier: Operating System :: MacOS
Classifier: Operating System :: Microsoft :: Windows
Classifier: Operating System :: POSIX :: Linux
Classifier: Programming Language :: Python :: 3
Classifier: Programming Language :: Python :: 3.8
Classifier: Programming Language :: Python :: 3.9
Classifier: Programming Language :: Python :: 3.10
Classifier: Programming Language :: Python :: 3.11
Classifier: Programming Language :: Python :: 3.12
Requires-Dist: PySide6 (>=6.6.0,<7.0.0)
Requires-Dist: pyyaml (>=6.0.1,<7.0.0)
Project-URL: Bug Tracker, https://github.com/muziing/Py2exe-GUI/issues
Project-URL: Repository, https://github.com/muziing/Py2exe-GUI
